{
  "es": {
    "welcome": "Bienvenido a SMART-TDAH",
    "description": "Software para el Análisis Inteligente de Datos y el Apoyo en el Seguimiento de Pacientes con TDAH.",
    "email": "Correo electrónico",
    "course": "Curso",
    "gender": "Género",
    "chartTitle": "Gráfica de estadísticas",
    "tableTitle": "Tabla de estadísticas",
    "startDate": "Fecha Inicio",
    "endDate": "Fecha Fin",
    "duration": "Duración (segundos)",
    "corrects": "Aciertos",
    "errors": "Errores",
    "accuracyRatio": "Ratio de Aciertos",
    "game": "Juego",
    "difficulty": "Dificultad",
    "invalidDate": "Fecha inválida",
    "invalidTime": "Hora inválida",
    "invalidDuration": "Duración inválida",
    "noData": "No hay datos",
    "noTokenProvided": "No se proporcionó un token",
    "studentfetchError": "Error al obtener la lista de alumnos",
    "loading": "Cargando...",
    "studentList": "Lista de alumnos", 
    "filterBy": "Filtrar por",
    "name": "Nombre",
    "lastName": "Apellidos",
    "search": "Buscar...",
    "previous": "Anterior",
    "next": "Siguiente",
    "page": "Página",
    "of": "de",
    "pageSize": "Tamaño de página",
    "all": "Todos",
    "easy": "Fácil",
    "normal": "Normal",
    "hard": "Difícil",
    "letterExercise": "Ejercicio de Letras",
    "displacementExercise": "Ejercicio de Desplazamiento",
    "mathOperations": "Operaciones Matemáticas",
    "memorizeNumbers": "Memorizar Números",
    "matchFigures": "Emparejar Figuras",
    "equalNumbersExercise": "Ejercicio de Números Iguales",
    "filterByDate": "Filtrar por Fecha",
    "from": "Desde",
    "to": "Hasta",
    "statsTable": "Tabla de Estadísticas",
    "loginTitle": "Iniciar sesión",
    "password": "Contraseña",
    "loginButton": "Iniciar sesión",
    "invalidCredentials": "Credenciales inválidas",
    "noAccount": "¿No tienes una cuenta?",
    "signUp": "Regístrate",
    "fetchError": "Error al obtener los datos del perfil",
    "signUpTitle": "Regístrate",
    "signUpButton": "Regístrate",
    "signUpError": "Error al registrar un nuevo usuario",
    "requiredField": "Campo obligatorio",
    "requiredCurrentPassword": "Debes introducir tu contraseña actual",
    "requiredNewPassword": "Debes introducir una nueva contraseña",
    "requiredConfirmPassword": "Debes confirmar la nueva contraseña",
    "invalidEmail": "Correo electrónico no válido",
    "weakPassword": "La contraseña debe tener al menos 8 caracteres, una mayúscula, una minúscula y un número",
    "emailExists": "El email ya está registrado",
    "invalidStudentId": "ID de estudiante inválido",
    "downloadReport": "Descargar informe",
    "reportFileName": "informe_alumno",
    "reportError": "Error al generar el informe",
    "settingsTitle": "Configuración",
    "changePasswordTitle": "Cambiar Contraseña",
    "currentPassword": "Contraseña Actual",
    "newPassword": "Nueva Contraseña",
    "confirmNewPassword": "Confirmar Nueva Contraseña",
    "changePasswordButton": "Cambiar Contraseña",
    "passwordMismatch": "Las contraseñas no coinciden",
    "passwordChangeSuccess": "Contraseña cambiada con éxito",
    "passwordChangeError": "Error al cambiar la contraseña",
    "profileTitle": "Perfil",
    "chatAskPlaceholder": "Hazme una pregunta...",
    "profesoresTitle": "Gestión de profesores",
    "profesoresFetchError": "Error al cargar profesores",
    "profesoresPermisoSuccess": "Permiso actualizado correctamente",
    "profesoresPermisoError": "Error actualizando permiso",
    "profesoresDeleteConfirm": "¿Seguro que quieres eliminar este profesor? Esta acción no se puede deshacer.",
    "profesoresDeleteSuccess": "Profesor eliminado correctamente",
    "profesoresDeleteError": "Error eliminando profesor",
    "profesoresPermisoCol": "¿Puede gestionar alumnos?",
    "delete": "Eliminar",
    "addAlumnoTitle": "Añadir alumno",
    "searchByEmail": "Buscar por email",
    "add": "Añadir",
    "added": "Añadido",
    "addAlumnoSuccess": "Alumno añadido correctamente",
    "addAlumnoError": "Error al añadir alumno",
    "close": "Cerrar",
    "deleteAlumnoTooltip": "Eliminar alumno",
    "deleteAlumnoConfirm": "¿Seguro que quieres eliminar este alumno de tu lista?",
    "deleteAlumnoSuccess": "Alumno eliminado correctamente",
    "deleteAlumnoError": "Error al eliminar alumno",
    "cancel": "Cancelar"
  },
  "gal": {
    "welcome": "Benvido a SMART-TDAH",
    "description": "Software para a Análise Intelixente de Datos e Apoio no Seguimento de Pacientes con TDAH.",
    "email": "Correo electrónico",
    "course": "Curso",
    "gender": "Xénero",
    "chartTitle": "Gráfica de estatísticas",
    "tableTitle": "Táboa de estatísticas",
    "startDate": "Data de Inicio",
    "endDate": "Data de Fin",
    "duration": "Duración (segundos)",
    "corrects": "Acertos",
    "errors": "Erros",
    "accuracyRatio": "Taxa de acertos",
    "game": "Xogo",
    "difficulty": "Dificultade",
    "invalidDate": "Data non válida",
    "invalidTime": "Hora non válida",
    "invalidDuration": "Duración non válida",
    "noData": "Non hai datos",
    "noTokenProvided": "Non se proporcionou un token",
    "studentfetchError": "Erro ao obter a lista de alumnos",
    "loading": "Cargando...",
    "studentList": "Lista de alumnos",
    "filterBy": "Filtrar por",
    "name": "Nome",
    "lastName": "Apelidos",
    "search": "Buscar...",
    "previous": "Anterior",
    "next": "Seguinte",
    "page": "Páxina",
    "of": "de",
    "pageSize": "Tamaño de páxina",
    "all": "Todos",
    "easy": "Fácil",
    "normal": "Normal",
    "hard": "Difícil",
    "letterExercise": "Exercicio de Letras",
    "displacementExercise": "Exercicio de desprazamento",
    "mathOperations": "Operacións Matemáticas",
    "memorizeNumbers": "Memorizar Números",
    "matchFigures": "Emparellar Figuras",
    "equalNumbersExercise": "Exercicio de Números Iguais",
    "filterByDate": "Filtrar por Data",
    "from": "Dende",
    "to": "Ata",
    "statsTable": "Táboa de Estatísticas",
    "loginTitle": "Iniciar sesión",
    "password": "Contrasinal",
    "loginButton": "Iniciar sesión",
    "invalidCredentials": "Credenciais non válidas",
    "noAccount": "¿Non tes unha conta?",
    "signUp": "Rexístrate",
    "fetchError": "Erro ao obter os datos do perfil",
    "signUpTitle": "Rexístrate",
    "signUpButton": "Rexístrate",
    "signUpError": "Erro ao rexistrar un novo usuario",
    "requiredField": "Campo obrigatorio",
    "requiredCurrentPassword": "Debes introducir o teu contrasinal actual",
    "requiredNewPassword": "Debes introducir un novo contrasinal",
    "requiredConfirmPassword": "Debes confirmar o novo contrasinal",
    "invalidEmail": "Correo electrónico non válido",
    "weakPassword": "O contrasinal debe ter polo menos 8 caracteres, unha maiúscula, unha minúscula e un número",
    "emailExists": "O email xa está rexistrado",
    "invalidStudentId": "ID de estudante non válido",
    "downloadReport": "Descargar informe",
    "reportFileName": "informe_alumno",
    "reportError": "Erro ao xerar o informe",
    "settingsTitle": "Configuración",
    "changePasswordTitle": "Cambiar Contrasinal",
    "currentPassword": "Contrasinal Actual",
    "newPassword": "Novo Contrasinal",
    "confirmNewPassword": "Confirmar Novo Contrasinal",
    "changePasswordButton": "Cambiar Contrasinal",
    "passwordMismatch": "Os contrasinais non coinciden",
    "passwordChangeSuccess": "Contrasinal cambiado con éxito",
    "passwordChangeError": "Erro ao cambiar o contrasinal",
    "profileTitle": "Perfil",
    "chatAskPlaceholder": "Fai unha pregunta...",
    "profesoresTitle": "Xestión de profesores",
    "profesoresFetchError": "Erro ao cargar profesores",
    "profesoresPermisoSuccess": "Permiso actualizado correctamente",
    "profesoresPermisoError": "Erro ao actualizar o permiso",
    "profesoresDeleteConfirm": "Seguro que queres eliminar este profesor? Esta acción non se pode desfacer.",
    "profesoresDeleteSuccess": "Profesor eliminado correctamente",
    "profesoresDeleteError": "Erro ao eliminar o profesor",
    "profesoresPermisoCol": "Pode xestionar alumnos?",
    "delete": "Eliminar",
    "addAlumnoTitle": "Engadir alumno",
    "searchByEmail": "Buscar por correo",
    "add": "Engadir",
    "added": "Engadido",
    "addAlumnoSuccess": "Alumno engadido correctamente",
    "addAlumnoError": "Erro ao engadir alumno",
    "close": "Pechar",
    "deleteAlumnoTooltip": "Eliminar alumno",
    "deleteAlumnoConfirm": "Seguro que queres eliminar este alumno da túa lista?",
    "deleteAlumnoSuccess": "Alumno eliminado correctamente",
    "deleteAlumnoError": "Erro ao eliminar alumno",
    "cancel": "Cancelar"
  },
  "en": {
    "welcome": "Welcome to SMART-TDAH",
    "description": "Software for Intelligent Data Analysis and Support in Monitoring Patients with ADHD.",
    "email": "Email Address",
    "course": "Course",
    "gender": "Gender",
    "chartTitle": "Statistics Chart",
    "tableTitle": "Statistics Table",
    "startDate": "Start Date",
    "endDate": "End Date",
    "duration": "Duration (seconds)",
    "corrects": "Corrects",
    "errors": "Errors",
    "accuracyRatio": "Accuracy Ratio",
    "game": "Game",
    "difficulty": "Difficulty",
    "invalidDate": "Invalid Date",
    "invalidTime": "Invalid Time",
    "invalidDuration": "Invalid Duration",
    "noData": "No data", 
    "noTokenProvided": "No token provided",
    "studentfetchError": "Error fetching student list",
    "loading": "Loading...",
    "studentList": "Student List", 
    "filterBy": "Filter by",
    "name": "Name",
    "lastName": "Last Name",
    "search": "Search...",
    "previous": "Previous",
    "next": "Next",
    "page": "Page",
    "of": "of",
    "pageSize": "Page Size",
    "all": "All",
    "easy": "Easy",
    "normal": "Normal",
    "hard": "Hard",
    "letterExercise": "Letter Exercise",
    "displacementExercise": "Displacement Exercise",
    "mathOperations": "Math Operations",
    "memorizeNumbers": "Memorize Numbers",
    "matchFigures": "Match Figures",
    "equalNumbersExercise": "Equal Numbers Exercise",
    "filterByDate": "Filter by Date",
    "from": "From",
    "to": "To",
    "statsTable": "Statistics Table",
    "loginTitle": "Login",
    "password": "Password",
    "loginButton": "Login",
    "invalidCredentials": "Invalid credentials",
    "noAccount": "Don't have an account?",
    "signUp": "Sign Up",
    "fetchError": "Error fetching profile data",
    "signUpTitle": "Sign Up",
    "signUpButton": "Sign Up",
    "signUpError": "Error registering new user",
    "requiredField": "Required field",
    "requiredCurrentPassword": "You must enter your current password",
    "requiredNewPassword": "You must enter a new password",
    "requiredConfirmPassword": "You must confirm the new password",
    "invalidEmail": "Invalid email address",
    "weakPassword": "Password must be at least 8 characters, with uppercase, lowercase and a number",
    "emailExists": "Email is already registered",
    "invalidStudentId": "Invalid student ID",
    "downloadReport": "Download Report",
    "reportFileName": "student_report",
    "reportError": "Error generating report",
    "settingsTitle": "Settings",
    "changePasswordTitle": "Change Password",
    "currentPassword": "Current Password",
    "newPassword": "New Password",
    "confirmNewPassword": "Confirm New Password",
    "changePasswordButton": "Change Password",
    "passwordMismatch": "Passwords do not match",
    "passwordChangeSuccess": "Password changed successfully",
    "passwordChangeError": "Error changing password",
    "profileTitle": "Profile",
    "chatAskPlaceholder": "Ask me a question...",
    "profesoresTitle": "Teacher management",
    "profesoresFetchError": "Error loading teachers",
    "profesoresPermisoSuccess": "Permission updated successfully",
    "profesoresPermisoError": "Error updating permission",
    "profesoresDeleteConfirm": "Are you sure you want to delete this teacher? This action cannot be undone.",
    "profesoresDeleteSuccess": "Teacher deleted successfully",
    "profesoresDeleteError": "Error deleting teacher",
    "profesoresPermisoCol": "Can manage students?",
    "delete": "Delete",
    "addAlumnoTitle": "Add student",
    "searchByEmail": "Search by email",
    "add": "Add",
    "added": "Added",
    "addAlumnoSuccess": "Student added successfully",
    "addAlumnoError": "Error adding student",
    "close": "Close",
    "deleteAlumnoTooltip": "Remove student",
    "deleteAlumnoConfirm": "Are you sure you want to remove this student from your list?",
    "deleteAlumnoSuccess": "Student removed successfully",
    "deleteAlumnoError": "Error removing student",
    "cancel": "Cancel"
  },
  "pt": {
    "welcome": "Bem-vindo ao SMART-TDAH",
    "description": "Software para Análise Inteligente de Dados e Suporte no Monitoramento de Pacientes com TDAH.",
    "email": "Endereço de Email",
    "course": "Curso",
    "gender": "Gênero",
    "chartTitle": "Gráfico de Estatísticas",
    "tableTitle": "Tabela de Estatísticas",
    "startDate": "Data de Início",
    "endDate": "Data de Fim",
    "duration": "Duração (segundos)",
    "corrects": "Acertos",
    "errors": "Erros",
    "accuracyRatio": "Taxa de Acertos",
    "game": "Jogo",
    "difficulty": "Dificuldade",
    "invalidDate": "Data inválida",
    "invalidTime": "Hora inválida",
    "invalidDuration": "Duração inválida",
    "noData": "Sem dados", 
    "noTokenProvided": "Nenhum token fornecido",
    "studentfetchError": "Erro ao buscar a lista de alunos",
    "loading": "Carregando...",
    "studentList": "Lista de alunos", 
    "filterBy": "Filtrar por",
    "name": "Nome",
    "lastName": "Sobrenome",
    "search": "Pesquisar...",
    "previous": "Anterior",
    "next": "Próximo",
    "page": "Página",
    "of": "de",
    "pageSize": "Tamanho da página",
    "all": "Todos",
    "easy": "Fácil",
    "normal": "Normal",
    "hard": "Difícil",
    "letterExercise": "Exercício de Letras",
    "displacementExercise": "Exercício de Deslocamento",
    "mathOperations": "Operações Matemáticas",
    "memorizeNumbers": "Memorizar Números",
    "matchFigures": "Combinar Figuras",
    "equalNumbersExercise": "Exercício de Números Iguais",
    "filterByDate": "Filtrar por Data",
    "from": "De",
    "to": "Até",
    "statsTable": "Tabela de Estatísticas",
    "loginTitle": "Entrar",
    "password": "Senha",
    "loginButton": "Entrar",
    "invalidCredentials": "Credenciais inválidas",
    "noAccount": "Não tem uma conta?",
    "signUp": "Cadastre-se",
    "fetchError": "Erro ao buscar os dados do perfil",
    "signUpTitle": "Cadastre-se",
    "signUpButton": "Cadastre-se",
    "signUpError": "Erro ao registrar um novo usuário",
    "requiredField": "Campo obrigatório",
    "requiredCurrentPassword": "Você deve inserir sua senha atual",
    "requiredNewPassword": "Você deve inserir uma nova senha",
    "requiredConfirmPassword": "Você deve confirmar a nova senha",
    "invalidEmail": "Endereço de email inválido",
    "weakPassword": "A senha deve ter pelo menos 8 caracteres, uma maiúscula, uma minúscula e um número",
    "emailExists": "O email já está cadastrado",
    "invalidStudentId": "ID de estudante inválido",
    "downloadReport": "Baixar Relatório",
    "reportFileName": "relatorio_estudante",
    "reportError": "Erro ao gerar o relatório",
    "settingsTitle": "Configurações",
    "changePasswordTitle": "Alterar Senha",
    "currentPassword": "Senha Atual",
    "newPassword": "Nova Senha",
    "confirmNewPassword": "Confirmar Nova Senha",
    "changePasswordButton": "Alterar Senha",
    "passwordMismatch": "As senhas não coincidem",
    "passwordChangeSuccess": "Senha alterada com sucesso",
    "passwordChangeError": "Erro ao alterar a senha",
    "profileTitle": "Perfil",
    "chatAskPlaceholder": "Faça-me uma pergunta...",
    "profesoresTitle": "Gestão de professores",
    "profesoresFetchError": "Erro ao carregar professores",
    "profesoresPermisoSuccess": "Permissão atualizada com sucesso",
    "profesoresPermisoError": "Erro ao atualizar permissão",
    "profesoresDeleteConfirm": "Tem certeza de que deseja excluir este professor? Esta ação não pode ser desfeita.",
    "profesoresDeleteSuccess": "Professor excluído com sucesso",
    "profesoresDeleteError": "Erro ao excluir professor",
    "profesoresPermisoCol": "Pode gerir alunos?",
    "delete": "Excluir",
    "addAlumnoTitle": "Adicionar aluno",
    "searchByEmail": "Buscar por email",
    "add": "Adicionar",
    "added": "Adicionado",
    "addAlumnoSuccess": "Aluno adicionado com sucesso",
    "addAlumnoError": "Erro ao adicionar aluno",
    "close": "Fechar",
    "deleteAlumnoTooltip": "Excluir aluno",
    "deleteAlumnoConfirm": "Tem certeza de que deseja remover este aluno da sua lista?",
    "deleteAlumnoSuccess": "Aluno removido com sucesso",
    "deleteAlumnoError": "Erro ao remover aluno",
    "cancel": "Cancelar"
  }
}